[
  {
    "$type": "SchoolStaffManagerApp.TeachingStaff, SchoolStaffManagerApp",
    "Subject": "maths",
    "AssignedClass": "10",
    "StaffId": 1,
    "Name": "Stu",
    "Address": {
      "HouseName": "abc",
      "AddressLine1": "def",
      "AddressLine2": "ghi",
      "Pin": 670670
    },
    "PhoneNumber": 1231231231,
    "Salary": 35000.0,
    "StaffType": 0
  },
  {
    "$type": "SchoolStaffManagerApp.AdminstrativeStaff, SchoolStaffManagerApp",
    "Post": "Manager",
    "StaffId": 2,
    "Name": "Franny",
    "Address": {
      "HouseName": "qwe",
      "AddressLine1": "asd",
      "AddressLine2": "asd",
      "Pin": 678678
    },
    "PhoneNumber": 9667787887,
    "Salary": 50000.0,
    "StaffType": 1
  }
]